jira_assistant_skills_lib/__init__.py
jira_assistant_skills_lib/adf_helper.py
jira_assistant_skills_lib/autocomplete_cache.py
jira_assistant_skills_lib/automation_client.py
jira_assistant_skills_lib/batch_processor.py
jira_assistant_skills_lib/cache.py
jira_assistant_skills_lib/config_manager.py
jira_assistant_skills_lib/constants.py
jira_assistant_skills_lib/credential_manager.py
jira_assistant_skills_lib/error_handler.py
jira_assistant_skills_lib/formatters.py
jira_assistant_skills_lib/jira_client.py
jira_assistant_skills_lib/mock_responses.py
jira_assistant_skills_lib/permission_helpers.py
jira_assistant_skills_lib/project_context.py
jira_assistant_skills_lib/request_batcher.py
jira_assistant_skills_lib/search_helpers.py
jira_assistant_skills_lib/time_utils.py
jira_assistant_skills_lib/transition_helpers.py
jira_assistant_skills_lib/user_helpers.py
jira_assistant_skills_lib/validators.py
jira_assistant_skills_lib/cli/__init__.py
jira_assistant_skills_lib/cli/cli_utils.py
jira_assistant_skills_lib/cli/main.py
jira_assistant_skills_lib/cli/commands/__init__.py
jira_assistant_skills_lib/cli/commands/admin_cmds.py
jira_assistant_skills_lib/cli/commands/agile_cmds.py
jira_assistant_skills_lib/cli/commands/bulk_cmds.py
jira_assistant_skills_lib/cli/commands/collaborate_cmds.py
jira_assistant_skills_lib/cli/commands/dev_cmds.py
jira_assistant_skills_lib/cli/commands/fields_cmds.py
jira_assistant_skills_lib/cli/commands/issue_cmds.py
jira_assistant_skills_lib/cli/commands/jsm_cmds.py
jira_assistant_skills_lib/cli/commands/lifecycle_cmds.py
jira_assistant_skills_lib/cli/commands/ops_cmds.py
jira_assistant_skills_lib/cli/commands/relationships_cmds.py
jira_assistant_skills_lib/cli/commands/search_cmds.py
jira_assistant_skills_lib/cli/commands/time_cmds.py
jira_assistant_skills_lib/mock/__init__.py
jira_assistant_skills_lib/mock/base.py
jira_assistant_skills_lib/mock/clients.py
jira_assistant_skills_lib/mock/factories.py
jira_assistant_skills_lib/mock/protocols.py
jira_assistant_skills-1.2.0.dist-info/METADATA
jira_assistant_skills-1.2.0.dist-info/WHEEL
jira_assistant_skills-1.2.0.dist-info/entry_points.txt
jira_assistant_skills-1.2.0.dist-info/licenses/LICENSE
jira_assistant_skills-1.2.0.dist-info/RECORD
